backup_juggler/__init__.py
backup_juggler/files_manager.py
backup_juggler/juggler_cli.py
backup_juggler/paths_manager.py
backup_juggler/progress_viewer.py
backup_juggler-0.2.1.dist-info/entry_points.txt
backup_juggler-0.2.1.dist-info/LICENSE
backup_juggler-0.2.1.dist-info/METADATA
backup_juggler-0.2.1.dist-info/WHEEL
backup_juggler-0.2.1.dist-info/RECORD
