Metadata-Version: 2.1
Name: backup-juggler
Version: 0.2.1
Summary: Multiple copies of files and directories simultaneously made easy
License: GPL-3.0-only
Author: Marcos Raulino
Author-email: marcosfsraulino@gmail.com
Requires-Python: >=3.11,<4.0
Classifier: Development Status :: 5 - Production/Stable
Classifier: Environment :: Console
Classifier: Intended Audience :: End Users/Desktop
Classifier: License :: OSI Approved :: GNU General Public License v3 (GPLv3)
Classifier: Natural Language :: English
Classifier: Operating System :: OS Independent
Classifier: Programming Language :: Python :: 3
Classifier: Programming Language :: Python :: 3.11
Classifier: Topic :: System :: Archiving :: Backup
Classifier: Topic :: Utilities
Requires-Dist: rich (>=13.4.2,<14.0.0)
Requires-Dist: toml (>=0.10.2,<0.11.0)
Requires-Dist: tqdm (>=4.65.0,<5.0.0)
Requires-Dist: typer[all] (>=0.9.0,<0.10.0)
Project-URL: Documentation, https://backup-juggler.readthedocs.io/en/latest/
Project-URL: Issue Tracker, https://github.com/raulin0/backup-juggler/issues
Project-URL: Repository, https://github.com/raulin0/backup-juggler
